etna_api/__init__.py
etna_api/__main__.py
etna_api/cli.py
etna_api/helpers.py
etna_api/types.py
etna_api-3.4.3.dist-info/LICENSE
etna_api-3.4.3.dist-info/METADATA
etna_api-3.4.3.dist-info/WHEEL
etna_api-3.4.3.dist-info/RECORD
